{"items":[{"published":"2007-01-04 00:00:00 -0800","title":"WWW::Mechanize で Vox に写真をアップロード","url":"http://blog.8-p.info/articles/2007/01/04/www-mechanize-vox","language":"ja"},{"published":"2007-01-04 00:00:00 -0800","title":"2007","url":"http://blog.8-p.info/articles/2007/01/04/2007","language":"ja"},{"published":"2007-01-07 00:00:00 -0800","title":"Celebrity's mouth","url":"http://blog.8-p.info/articles/2007/01/07/celebritys-mouth","language":"ja"},{"published":"2007-01-07 00:00:00 -0800","title":"hatebmap update","url":"http://blog.8-p.info/articles/2007/01/07/hatebmap-update","language":"ja"},{"published":"2007-01-08 00:00:00 -0800","title":"フィードの情報だけで HTML の title 要素と等価な文字列を","url":"http://blog.8-p.info/articles/2007/01/08/html-title","language":"ja"},{"published":"2007-01-08 00:00:00 -0800","title":"NSSpellChecker と NSApplication","url":"http://blog.8-p.info/articles/2007/01/08/nsspellchecker-nsapplication","language":"ja"},{"published":"2007-01-08 00:00:00 -0800","title":"無断リンク禁止を主張する tinycafe さんまわり","url":"http://blog.8-p.info/articles/2007/01/08/tinycafe","language":"ja"},{"published":"2007-01-08 00:00:00 -0800","title":"Finder の戻る/進むを Safari とそろえる","url":"http://blog.8-p.info/articles/2007/01/08/finder-safari","language":"ja"},{"published":"2007-01-11 00:00:00 -0800","title":"Podcastle Night","url":"http://blog.8-p.info/articles/2007/01/11/podcastle-night","language":"ja"},{"published":"2007-01-13 00:00:00 -0800","title":"mixi の「プライバシー警告」さん","url":"http://blog.8-p.info/articles/2007/01/13/mixi","language":"ja"},{"published":"2007-01-16 00:00:00 -0800","title":"Mac で LD_PRELOAD","url":"http://blog.8-p.info/articles/2007/01/16/mac-ld_preload","language":"ja"},{"published":"2007-01-21 00:00:00 -0800","title":"NHK で Google","url":"http://blog.8-p.info/articles/2007/01/21/nhk-google","language":"ja"},{"published":"2007-01-24 00:00:00 -0800","title":"Alan Kay の講演を読んだ","url":"http://blog.8-p.info/articles/2007/01/24/alan-kay","language":"ja"},{"published":"2007-01-28 00:00:00 -0800","title":"POOKGLOBE","url":"http://blog.8-p.info/articles/2007/01/28/pookglobe","language":"ja"},{"published":"2007-01-30 00:00:00 -0800","title":"Shinjuku typography","url":"http://blog.8-p.info/articles/2007/01/30/shinjuku-typography","language":"ja"},{"published":"2007-01-31 00:00:00 -0800","title":"Safari に RegExp.leftContext, RegExp.rightContext","url":"http://blog.8-p.info/articles/2007/01/31/safari-regexp-leftcontext-regexp-rightcontext","language":"ja"},{"published":"2007-02-04 00:00:00 -0800","title":"iBook を落とした","url":"http://blog.8-p.info/articles/2007/02/04/ibook","language":"ja"},{"published":"2007-02-05 00:00:00 -0800","title":"LLC のひとがきた","url":"http://blog.8-p.info/articles/2007/02/05/llc","language":"ja"},{"published":"2007-02-06 00:00:00 -0800","title":"PICkit 1 が届いた","url":"http://blog.8-p.info/articles/2007/02/06/pickit-1","language":"ja"},{"published":"2007-02-10 00:00:00 -0800","title":"Not driven by fanfare","url":"http://blog.8-p.info/articles/2007/02/10/not-driven-by-fanfare","language":"ja"},{"published":"2007-02-13 00:00:00 -0800","title":"Books I read recently","url":"http://blog.8-p.info/articles/2007/02/13/books-i-read-recently","language":"ja"},{"published":"2007-02-14 00:00:00 -0800","title":"ピースボートのバレンタインまとめ","url":"http://blog.8-p.info/articles/2007/02/14/peaceboat-valentine","language":"ja"},{"published":"2007-02-18 00:00:00 -0800","title":"Picture for my resume","url":"http://blog.8-p.info/articles/2007/02/18/picture-for-my-resume","language":"ja"},{"published":"2007-02-20 00:00:00 -0800","title":"iBook が帰ってきた","url":"http://blog.8-p.info/articles/2007/02/20/ibook","language":"ja"},{"published":"2007-02-22 00:00:00 -0800","title":"日本語環境の iTerm で option キーを meta キーにする","url":"http://blog.8-p.info/articles/2007/02/22/iterm-option-meta","language":"ja"},{"published":"2007-02-22 00:00:00 -0800","title":"NSURL なんとかで cookie を共有","url":"http://blog.8-p.info/articles/2007/02/22/nsurl-cookie","language":"ja"},{"published":"2007-02-25 00:00:00 -0800","title":"複数の bookmarklet をまとめる → それ blummy で","url":"http://blog.8-p.info/articles/2007/02/25/bookmarklet-blummy","language":"ja"},{"published":"2007-03-01 00:00:00 -0800","title":"March","url":"http://blog.8-p.info/articles/2007/03/01/march","language":"ja"},{"published":"2007-03-06 00:00:00 -0800","title":"学校では教えてくれないなんとか英語: Creammonkey","url":"http://blog.8-p.info/articles/2007/03/06/creammonkey","language":"ja"},{"published":"2007-03-06 00:00:00 -0800","title":"Creammonkey の GM_XHR","url":"http://blog.8-p.info/articles/2007/03/06/creammonkey-gm_xhr","language":"ja"},{"published":"2007-03-12 00:00:00 -0700","title":"mF247 に Quinka, with a Yawn","url":"http://blog.8-p.info/articles/2007/03/12/mf247-quinka-with-a-yawn","language":"ja"},{"published":"2007-03-15 00:00:00 -0700","title":"SpiderMonkey に自分のコードがはいった","url":"http://blog.8-p.info/articles/2007/03/15/spidermonkey","language":"ja"},{"published":"2007-03-20 00:00:00 -0700","title":"Job hunting","url":"http://blog.8-p.info/articles/2007/03/20/job-hunting","language":"ja"},{"published":"2007-03-20 00:00:00 -0700","title":"Apollo が WebKit for Win32 をもってる件","url":"http://blog.8-p.info/articles/2007/03/20/apollo-webkit-for-win32","language":"ja"},{"published":"2007-03-22 00:00:00 -0700","title":"Plagger のインストールを自動化する","url":"http://blog.8-p.info/articles/2007/03/22/plagger","language":"ja"},{"published":"2007-03-24 00:00:00 -0700","title":"Shibuya.js Technical Talk #3","url":"http://blog.8-p.info/articles/2007/03/24/shibuya-js-technical-talk-3","language":"ja"},{"published":"2007-03-24 00:00:00 -0700","title":"InputManager on Leopard","url":"http://blog.8-p.info/articles/2007/03/24/inputmanager-on-leopard","language":"ja"},{"published":"2007-03-25 00:00:00 -0700","title":"Yet another InputManager hole","url":"http://blog.8-p.info/articles/2007/03/25/yet-another-inputmanager-hole","language":"ja"},{"published":"2007-03-29 00:00:00 -0700","title":"Greasekelly","url":"http://blog.8-p.info/articles/2007/03/29/greasekelly","language":"ja"},{"published":"2007-04-01 00:00:00 -0700","title":"April","url":"http://blog.8-p.info/articles/2007/04/01/april","language":"ja"},{"published":"2007-04-01 00:00:00 -0700","title":"sabra で Second Life 特集","url":"http://blog.8-p.info/articles/2007/04/01/sabra-second-life","language":"ja"},{"published":"2007-04-05 00:00:00 -0700","title":"Dashboard のセキュリティモデル","url":"http://blog.8-p.info/articles/2007/04/05/dashboard","language":"ja"},{"published":"2007-04-10 00:00:00 -0700","title":"Twitter はじめた","url":"http://blog.8-p.info/articles/2007/04/10/twitter","language":"ja"},{"published":"2007-04-14 00:00:00 -0700","title":"New Culturism Manifesto","url":"http://blog.8-p.info/articles/2007/04/14/new-culturism-manifesto","language":"ja"},{"published":"2007-04-17 00:00:00 -0700","title":"Bug 5353 fixed!","url":"http://blog.8-p.info/articles/2007/04/17/bug-5353-fixed","language":"ja"},{"published":"2007-04-22 00:00:00 -0700","title":"Unlocalize.mdimporter 0.2","url":"http://blog.8-p.info/articles/2007/04/22/unlocalize-mdimporter-0-2","language":"ja"},{"published":"2007-04-22 00:00:00 -0700","title":"Twitter つづき","url":"http://blog.8-p.info/articles/2007/04/22/twitter","language":"ja"},{"published":"2007-04-27 00:00:00 -0700","title":"37signals にはいるか、なるか","url":"http://blog.8-p.info/articles/2007/04/27/37signals","language":"ja"},{"published":"2007-04-29 00:00:00 -0700","title":"Tokyo Toybox","url":"http://blog.8-p.info/articles/2007/04/29/tokyo-toybox","language":"ja"},{"published":"2007-05-05 00:00:00 -0700","title":"Twitter can't protect your updates","url":"http://blog.8-p.info/articles/2007/05/05/twitter-cant-protect-your-updates","language":"ja"},{"published":"2007-05-06 00:00:00 -0700","title":"svn.8-p.info","url":"http://blog.8-p.info/articles/2007/05/06/svn-8-p-info","language":"ja"},{"published":"2007-05-06 00:00:00 -0700","title":"Plagger 0.7.17 for Mac","url":"http://blog.8-p.info/articles/2007/05/06/plagger-0-7-17-for-mac","language":"ja"},{"published":"2007-05-10 00:00:00 -0700","title":"wtf","url":"http://blog.8-p.info/articles/2007/05/10/wtf","language":"ja"},{"published":"2007-05-11 00:00:00 -0700","title":"Super Deluxe に行くよ","url":"http://blog.8-p.info/articles/2007/05/11/super-deluxe","language":"ja"},{"published":"2007-05-12 00:00:00 -0700","title":"Built with Processing","url":"http://blog.8-p.info/articles/2007/05/12/built-with-processing","language":"ja"},{"published":"2007-05-16 00:00:00 -0700","title":"Shibuya","url":"http://blog.8-p.info/articles/2007/05/16/shibuya","language":"ja"},{"published":"2007-05-19 00:00:00 -0700","title":"Why blogging","url":"http://blog.8-p.info/articles/2007/05/19/why-blogging","language":"ja"},{"published":"2007-05-23 00:00:00 -0700","title":"Twitter の JSONP のキャッシュ","url":"http://blog.8-p.info/articles/2007/05/23/twitter-jsonp","language":"ja"},{"published":"2007-05-25 00:00:00 -0700","title":"How to Become a Pro.","url":"http://blog.8-p.info/articles/2007/05/25/how-to-become-a-pro","language":"ja"},{"published":"2007-05-26 00:00:00 -0700","title":"Tumblet に日本語を通す","url":"http://blog.8-p.info/articles/2007/05/26/tumblet","language":"ja"},{"published":"2007-05-28 00:00:00 -0700","title":"Comet 勉強会","url":"http://blog.8-p.info/articles/2007/05/28/comet","language":"ja"},{"published":"2007-05-31 00:00:00 -0700","title":"elbow grease?","url":"http://blog.8-p.info/articles/2007/05/31/elbow-grease","language":"ja"},{"published":"2007-06-01 00:00:00 -0700","title":"Google Gears は Safari もそのうち","url":"http://blog.8-p.info/articles/2007/06/01/google-gears-safari","language":"ja"},{"published":"2007-06-05 00:00:00 -0700","title":"Spahack #1","url":"http://blog.8-p.info/articles/2007/06/05/spahack-1","language":"ja"},{"published":"2007-06-12 00:00:00 -0700","title":"来年の RubyKaigi は行く","url":"http://blog.8-p.info/articles/2007/06/12/rubykaigi","language":"ja"},{"published":"2007-06-12 00:00:00 -0700","title":"Non-Programmer's Programming Book","url":"http://blog.8-p.info/articles/2007/06/12/non-programmers-programming-book","language":"ja"},{"published":"2007-06-14 00:00:00 -0700","title":"getMatchedCSSRules の第三引数","url":"http://blog.8-p.info/articles/2007/06/14/getmatchedcssrules","language":"ja"},{"published":"2007-06-17 00:00:00 -0700","title":"Creammonkey 0.9","url":"http://blog.8-p.info/articles/2007/06/17/creammonkey-0-9","language":"ja"},{"published":"2007-06-25 00:00:00 -0700","title":"Find","url":"http://blog.8-p.info/articles/2007/06/25/find","language":"ja"},{"published":"2007-06-25 00:00:00 -0700","title":"Opera について","url":"http://blog.8-p.info/articles/2007/06/25/opera","language":"ja"},{"published":"2007-06-26 00:00:00 -0700","title":"Comet 勉強会 #2","url":"http://blog.8-p.info/articles/2007/06/26/comet-2","language":"ja"},{"published":"2007-06-26 00:00:00 -0700","title":"Excuse","url":"http://blog.8-p.info/articles/2007/06/26/excuse","language":"ja"},{"published":"2007-06-28 00:00:00 -0700","title":"ICC「ネットワークの現在：世界はどうつながりうるのか」","url":"http://blog.8-p.info/articles/2007/06/28/icc","language":"ja"},{"published":"2007-06-29 00:00:00 -0700","title":"mixi に写真をアップロードする","url":"http://blog.8-p.info/articles/2007/06/29/mixi","language":"ja"},{"published":"2007-07-05 00:00:00 -0700","title":"talby が水没した","url":"http://blog.8-p.info/articles/2007/07/05/talby","language":"ja"},{"published":"2007-07-07 00:00:00 -0700","title":"UNIQLOCK MP3","url":"http://blog.8-p.info/articles/2007/07/07/uniqlock-mp3","language":"ja"},{"published":"2007-07-08 00:00:00 -0700","title":"Mephisto に移行","url":"http://blog.8-p.info/articles/2007/07/08/mephisto","language":"ja"},{"published":"2007-07-10 00:00:00 -0700","title":"Wildcard","url":"http://blog.8-p.info/articles/2007/07/10/wildcard","language":"ja"},{"published":"2007-07-12 00:00:00 -0700","title":"mixi デコリンクと JSON API","url":"http://blog.8-p.info/articles/2007/07/12/mixi-json-api","language":"ja"},{"published":"2007-07-15 00:00:00 -0700","title":"Hatena Idea #15927","url":"http://blog.8-p.info/articles/2007/07/15/hatena-idea-15927","language":"ja"},{"published":"2007-07-19 00:00:00 -0700","title":"Domain expired","url":"http://blog.8-p.info/articles/2007/07/19/domain-expired","language":"ja"},{"published":"2007-07-22 00:00:00 -0700","title":"Creammonkey 1.0","url":"http://blog.8-p.info/articles/2007/07/22/creammonkey-1-0","language":"ja"},{"published":"2007-07-24 00:00:00 -0700","title":"Creator's happiness","url":"http://blog.8-p.info/articles/2007/07/24/creators-happiness","language":"ja"},{"published":"2007-07-29 00:00:00 -0700","title":"Vote","url":"http://blog.8-p.info/articles/2007/07/29/vote","language":"ja"},{"published":"2007-07-31 00:00:00 -0700","title":"A computer should be on every desktop","url":"http://blog.8-p.info/articles/2007/07/31/a-computer-should-be-on-every-desktop","language":"ja"},{"published":"2007-08-05 00:00:00 -0700","title":"『2ちゃんねるはなぜ潰れないのか？』を読んだ","url":"http://blog.8-p.info/articles/2007/08/05/2ch","language":"ja"},{"published":"2007-08-13 00:00:00 -0700","title":"Motocompo を下北沢でみた","url":"http://blog.8-p.info/articles/2007/08/13/motocompo","language":"ja"},{"published":"2007-08-18 00:00:00 -0700","title":"Ruby で GAINER","url":"http://blog.8-p.info/articles/2007/08/18/ruby-gainer","language":"ja"},{"published":"2007-08-26 00:00:00 -0700","title":"SEE OSD","url":"http://blog.8-p.info/articles/2007/08/26/see-osd","language":"ja"},{"published":"2007-09-04 00:00:00 -0700","title":"MozRepl でテストつき Firefox プログラミング","url":"http://blog.8-p.info/articles/2007/09/04/mozrepl-firefox","language":"ja"},{"published":"2007-09-05 00:00:00 -0700","title":"mozrepl-test から汚染を除去","url":"http://blog.8-p.info/articles/2007/09/05/mozrepl-test","language":"ja"},{"published":"2007-09-16 00:00:00 -0700","title":"Creammonkey の名前問題","url":"http://blog.8-p.info/articles/2007/09/16/creammonkey","language":"ja"},{"published":"2007-09-16 00:00:00 -0700","title":"Mozilla 24","url":"http://blog.8-p.info/articles/2007/09/16/mozilla-24","language":"ja"},{"published":"2007-09-18 00:00:00 -0700","title":"いまさらの自分 CMS","url":"http://blog.8-p.info/articles/2007/09/18/cms","language":"ja"},{"published":"2007-09-18 00:00:00 -0700","title":"Google Code Prettify の複数言語対応","url":"http://blog.8-p.info/articles/2007/09/18/google-code-prettify","language":"ja"}]}